setup.py
rSubs/__init__.py
rSubs/config.py
rSubs/http_dns.py
rSubs/main.py
rSubs/subtitle_downloader.py
rSubs.egg-info/PKG-INFO
rSubs.egg-info/SOURCES.txt
rSubs.egg-info/dependency_links.txt
rSubs.egg-info/entry_points.txt
rSubs.egg-info/not-zip-safe
rSubs.egg-info/requires.txt
rSubs.egg-info/top_level.txt